starwardob/__init__.py
starwardob/starwardob.py
starwar_dob-3.141.post0.dist-info/LICENSE
starwar_dob-3.141.post0.dist-info/METADATA
starwar_dob-3.141.post0.dist-info/WHEEL
starwar_dob-3.141.post0.dist-info/top_level.txt
starwar_dob-3.141.post0.dist-info/RECORD
