Metadata-Version: 2.1
Name: starwar-dob
Version: 3.141.post0
Summary: for Starwar lover, Converter Starwar Calendar to Human readable Year
Home-page: https://github.com/blueband/starwar-calender-converter
Author: Qamarudeen Muhammad
Author-email: qamarudeen.m@gmail.com
License: UNKNOWN
Project-URL: Bug Tracker, https://github.com/blueband/starwar-calender-converter/issues
Platform: UNKNOWN
Classifier: Programming Language :: Python :: 3
Classifier: License :: OSI Approved :: MIT License
Classifier: Operating System :: OS Independent
Requires-Python: >=3.9
License-File: LICENSE
